shoebill_ai/__init__.py
shoebill_ai/application/__init__.py
shoebill_ai/application/messaging/__init__.py
shoebill_ai/application/messaging/graph_service.py
shoebill_ai/application/messaging/telegram_service.py
shoebill_ai/application/messaging/twitter_service.py
shoebill_ai/application/messaging/vector_db_service.py
shoebill_ai/application/messaging/web_service.py
shoebill_ai/domain/__init__.py
shoebill_ai/domain/agents/__init__.py
shoebill_ai/domain/agents/embedding_agent.py
shoebill_ai/domain/agents/hf_endpoint_service.py
shoebill_ai/domain/agents/multimodal_agent.py
shoebill_ai/domain/agents/text_agent.py
shoebill_ai/domain/agents/vision_agent.py
shoebill_ai/domain/agents/interfaces/__init__.py
shoebill_ai/domain/agents/interfaces/base_repository.py
shoebill_ai/domain/agents/interfaces/llm_chat_repository.py
shoebill_ai/domain/agents/interfaces/llm_embedding_repository.py
shoebill_ai/domain/agents/interfaces/model_factory.py
shoebill_ai/domain/messaging/__init__.py
shoebill_ai/domain/messaging/request_message_topic.py
shoebill_ai/domain/messaging/flows/__init__.py
shoebill_ai/domain/messaging/flows/event_message_topic.py
shoebill_ai/domain/messaging/flows/init_knowledgebase_request.py
shoebill_ai/domain/messaging/graph/__init__.py
shoebill_ai/domain/messaging/graph/graph_announcement_nodes_since_timestamp_request_message.py
shoebill_ai/domain/messaging/graph/graph_announcement_nodes_since_timestamp_response_message.py
shoebill_ai/domain/messaging/graph/graph_clear_request_message.py
shoebill_ai/domain/messaging/graph/graph_count_relationships_request_message.py
shoebill_ai/domain/messaging/graph/graph_count_relationships_response_message.py
shoebill_ai/domain/messaging/graph/graph_cypher_query_request_message.py
shoebill_ai/domain/messaging/graph/graph_cypher_query_response_message.py
shoebill_ai/domain/messaging/graph/graph_event_nodes_since_timestamp_request_message.py
shoebill_ai/domain/messaging/graph/graph_event_nodes_since_timestamp_response_message.py
shoebill_ai-0.0.110.dist-info/licenses/LICENSE
shoebill_ai-0.0.110.dist-info/licenses/NOTICE.txt
shoebill_ai-0.0.110.dist-info/METADATA
shoebill_ai-0.0.110.dist-info/WHEEL
shoebill_ai-0.0.110.dist-info/top_level.txt
shoebill_ai-0.0.110.dist-info/RECORD
