Metadata-Version: 2.4
Name: shoebill_ai
Version: 0.0.110
Summary: AI Agent Framework
Author-email: shoebill <shoebill.hai@gmail.com>
Classifier: Programming Language :: Python :: 3
Classifier: License :: OSI Approved :: Apache Software License
Classifier: Operating System :: OS Independent
Requires-Python: >=3.10
License-File: LICENSE
License-File: NOTICE.txt
Requires-Dist: requests~=2.32.5
Requires-Dist: pillow~=11.3.0
Requires-Dist: ollama~=0.5.3
Requires-Dist: openai~=1.12.0
Requires-Dist: huggingface_hub~=0.35.3
Requires-Dist: h_message_bus~=0.0.41
Requires-Dist: croniter~=6.0.0
Requires-Dist: pytz~=2025.2
Requires-Dist: numpy~=2.2.6
Provides-Extra: dev
Requires-Dist: pytest; extra == "dev"
Requires-Dist: pytest-mock; extra == "dev"
Dynamic: license-file
